odoo/addons/hr_holidays_public_city/README.rst
odoo/addons/hr_holidays_public_city/__init__.py
odoo/addons/hr_holidays_public_city/__manifest__.py
odoo/addons/hr_holidays_public_city/i18n/es.po
odoo/addons/hr_holidays_public_city/i18n/hr_holidays_public_city.pot
odoo/addons/hr_holidays_public_city/i18n/it.po
odoo/addons/hr_holidays_public_city/models/__init__.py
odoo/addons/hr_holidays_public_city/models/hr_holidays_public.py
odoo/addons/hr_holidays_public_city/models/hr_leave.py
odoo/addons/hr_holidays_public_city/readme/CONTRIBUTORS.rst
odoo/addons/hr_holidays_public_city/readme/DESCRIPTION.rst
odoo/addons/hr_holidays_public_city/static/description/icon.png
odoo/addons/hr_holidays_public_city/static/description/index.html
odoo/addons/hr_holidays_public_city/tests/__init__.py
odoo/addons/hr_holidays_public_city/tests/test_holidays_calculation.py
odoo/addons/hr_holidays_public_city/tests/test_holidays_public.py
odoo/addons/hr_holidays_public_city/views/hr_holidays_public_view.xml
odoo14_addon_hr_holidays_public_city-14.0.1.0.1.dev5.dist-info/METADATA
odoo14_addon_hr_holidays_public_city-14.0.1.0.1.dev5.dist-info/WHEEL
odoo14_addon_hr_holidays_public_city-14.0.1.0.1.dev5.dist-info/top_level.txt
odoo14_addon_hr_holidays_public_city-14.0.1.0.1.dev5.dist-info/RECORD
